teneva_bm/__init__.py
teneva_bm/bm.py
teneva_bm/agent/__init__.py
teneva_bm/agent/agent.py
teneva_bm/agent/bm_agent_ant.py
teneva_bm/agent/bm_agent_cheetah.py
teneva_bm/agent/bm_agent_human.py
teneva_bm/agent/bm_agent_human_stand.py
teneva_bm/agent/bm_agent_lake.py
teneva_bm/agent/bm_agent_lander.py
teneva_bm/agent/bm_agent_pend_inv.py
teneva_bm/agent/bm_agent_pend_inv_double.py
teneva_bm/agent/bm_agent_reacher.py
teneva_bm/agent/bm_agent_swimmer.py
teneva_bm/agent/policy.py
teneva_bm/decomp/__init__.py
teneva_bm/decomp/bm_decomp_ht.py
teneva_bm/decomp/bm_decomp_peps.py
teneva_bm/decomp/bm_decomp_tt.py
teneva_bm/func/__init__.py
teneva_bm/func/bm_func_ackley.py
teneva_bm/func/bm_func_alpine.py
teneva_bm/func/bm_func_chung.py
teneva_bm/func/bm_func_dixon.py
teneva_bm/func/bm_func_exp.py
teneva_bm/func/bm_func_griewank.py
teneva_bm/func/bm_func_michalewicz.py
teneva_bm/func/bm_func_pathological.py
teneva_bm/func/bm_func_pinter.py
teneva_bm/func/bm_func_powell.py
teneva_bm/func/bm_func_qing.py
teneva_bm/func/bm_func_rastrigin.py
teneva_bm/func/bm_func_rosenbrock.py
teneva_bm/func/bm_func_salomon.py
teneva_bm/func/bm_func_schaffer.py
teneva_bm/func/bm_func_schwefel.py
teneva_bm/func/bm_func_sphere.py
teneva_bm/func/bm_func_squares.py
teneva_bm/func/bm_func_trid.py
teneva_bm/func/bm_func_trigonometric.py
teneva_bm/func/bm_func_wavy.py
teneva_bm/func/bm_func_yang.py
teneva_bm/func/func.py
teneva_bm/func_fix/__init__.py
teneva_bm/func_fix/bm_func_fix_biggs.py
teneva_bm/func_fix/bm_func_fix_cantrell.py
teneva_bm/func_fix/bm_func_fix_colville.py
teneva_bm/func_fix/bm_func_fix_dolan.py
teneva_bm/func_fix/bm_func_fix_piston.py
teneva_bm/func_fix/func_fix.py
teneva_bm/hs/__init__.py
teneva_bm/hs/bm_hs_func001.py
teneva_bm/hs/bm_hs_func002.py
teneva_bm/hs/bm_hs_func003.py
teneva_bm/hs/bm_hs_func004.py
teneva_bm/hs/bm_hs_func005.py
teneva_bm/hs/bm_hs_func006.py
teneva_bm/hs/bm_hs_func007.py
teneva_bm/hs/bm_hs_func008.py
teneva_bm/hs/bm_hs_func009.py
teneva_bm/hs/bm_hs_func010.py
teneva_bm-0.9.1.dist-info/LICENSE
teneva_bm-0.9.1.dist-info/METADATA
teneva_bm-0.9.1.dist-info/WHEEL
teneva_bm-0.9.1.dist-info/top_level.txt
teneva_bm-0.9.1.dist-info/RECORD
