Metadata-Version: 2.1
Name: teneva-bm
Version: 0.9.1
Summary: Benchmarks library, based on the package teneva, for testing multivariate approximation and optimization methods
Home-page: https://github.com/AIRI-Institute/teneva_bm
Author: Andrei Chertkov
Author-email: andre.chertkov@gmail.com
License: MIT
Project-URL: Source, https://github.com/AIRI-Institute/teneva_bm
Keywords: benchmarks approximation optimization multidimensional array multivariate function low-rank representation tensor train format TT-decomposition
Classifier: Development Status :: 4 - Beta
Classifier: License :: OSI Approved :: MIT License
Classifier: Topic :: Scientific/Engineering
Classifier: Topic :: Scientific/Engineering :: Mathematics
Classifier: Topic :: Scientific/Engineering :: Information Analysis
Classifier: Topic :: Scientific/Engineering :: Artificial Intelligence
Classifier: Intended Audience :: Science/Research
Classifier: Operating System :: OS Independent
Classifier: Programming Language :: Python :: 3
Classifier: Programming Language :: Python :: 3 :: Only
Classifier: Programming Language :: Python :: 3.8
Classifier: Programming Language :: Python :: 3.9
Classifier: Programming Language :: Python :: 3.10
Classifier: Programming Language :: Python :: 3.11
Requires-Python: >=3.8
License-File: LICENSE
Requires-Dist: teneva>=0.14.7
Requires-Dist: contourpy==1.1.1; python_version == "3.8"
Requires-Dist: matplotlib<3.7.1,>=3.7.0; python_version == "3.8"
Requires-Dist: numpy<1.25,>=1.22; python_version == "3.8"
Requires-Dist: matplotlib>=3.7.0; python_version >= "3.9"
Requires-Dist: numpy>=1.22; python_version >= "3.9"
